beaverstudio-0.1.0.dist-info/METADATA
beaverstudio-0.1.0.dist-info/WHEEL
beaverstudio/__init__.py
beaverstudio/beaverstudio.cpython-312-x86_64-linux-gnu.so
beaverstudio-0.1.0.dist-info/RECORD
